tomos/__init__.py
tomos/ayed2/__init__.py
tomos/ayed2/ast/__init__.py
tomos/ayed2/ast/base.py
tomos/ayed2/ast/expressions.py
tomos/ayed2/ast/operators.py
tomos/ayed2/ast/program.py
tomos/ayed2/ast/sentences.py
tomos/ayed2/ast/types/__init__.py
tomos/ayed2/ast/types/array.py
tomos/ayed2/ast/types/basic.py
tomos/ayed2/ast/types/enum.py
tomos/ayed2/ast/types/registry.py
tomos/ayed2/ast/types/synonym.py
tomos/ayed2/ast/types/t_tuple.py
tomos/ayed2/evaluation/__init__.py
tomos/ayed2/evaluation/expressions.py
tomos/ayed2/evaluation/interpreter.py
tomos/ayed2/evaluation/limits.py
tomos/ayed2/evaluation/limits.toml
tomos/ayed2/evaluation/memory.py
tomos/ayed2/evaluation/persistency.py
tomos/ayed2/evaluation/state.py
tomos/ayed2/evaluation/unknown_value.py
tomos/ayed2/parser/__init__.py
tomos/ayed2/parser/grammar.abstract
tomos/ayed2/parser/grammar.lark
tomos/ayed2/parser/metadata.py
tomos/ayed2/parser/parsetree_to_ast.py
tomos/ayed2/parser/reserved_words.py
tomos/ayed2/parser/syntax_highlight.py
tomos/ayed2/parser/token.py
tomos/base_classes/__init__.py
tomos/base_classes/dataclasses.py
tomos/exceptions.py
tomos/ui/__init__.py
tomos/ui/cli.py
tomos/ui/colors.py
tomos/ui/interpreter_hooks/__init__.py
tomos/ui/interpreter_hooks/interactions.py
tomos/ui/interpreter_hooks/remember_state.py
tomos/ui/interpreter_hooks/show_ast.py
tomos/ui/interpreter_hooks/show_code.py
tomos/ui/interpreter_hooks/show_state.py
tomos/ui/movie/__init__.py
tomos/ui/movie/builder.py
tomos/ui/movie/panel/__init__.py
tomos/ui/movie/panel/code.py
tomos/ui/movie/panel/memory.py
tomos/ui/movie/panel/pointer_arrows.py
tomos/ui/movie/panel/vars.py
tomos/ui/movie/scene.py
tomos/ui/movie/texts.py
tomos/ui/movie/tomos_ui.toml
tomos/ui/patch_moviepy.py
tomos/visit.py
tomos-0.1.6.dist-info/LICENSE
tomos-0.1.6.dist-info/METADATA
tomos-0.1.6.dist-info/WHEEL
tomos-0.1.6.dist-info/entry_points.txt
tomos-0.1.6.dist-info/RECORD
